pocketutils/__init__.py
pocketutils/biochem/__init__.py
pocketutils/biochem/atc_tree.py
pocketutils/biochem/multiwell_plate_rois.py
pocketutils/biochem/multiwell_plates.py
pocketutils/biochem/tissue_expression.py
pocketutils/biochem/uniprot_go.py
pocketutils/core/__init__.py
pocketutils/core/_internal.py
pocketutils/core/chars.py
pocketutils/core/dot_dict.py
pocketutils/core/enums.py
pocketutils/core/exceptions.py
pocketutils/core/input_output.py
pocketutils/core/iterators.py
pocketutils/core/mocks.py
pocketutils/core/query_utils.py
pocketutils/full.py
pocketutils/misc/__init__.py
pocketutils/misc/j.py
pocketutils/misc/loguru_utils.py
pocketutils/misc/magic_template.py
pocketutils/misc/notifiers_utils.py
pocketutils/misc/resources.py
pocketutils/misc/typer_utils.py
pocketutils/misc/warning_utils.py
pocketutils/misc/web_resource.py
pocketutils/plotting/_bound_ticks.py
pocketutils/plotting/color_schemes.py
pocketutils/plotting/fig_savers.py
pocketutils/plotting/fig_tools.py
pocketutils/plotting/ref_dims.py
pocketutils/tools/__init__.py
pocketutils/tools/all_tools.py
pocketutils/tools/base_tools.py
pocketutils/tools/call_tools.py
pocketutils/tools/common_tools.py
pocketutils/tools/console_tools.py
pocketutils/tools/filesys_tools.py
pocketutils/tools/loop_tools.py
pocketutils/tools/numeric_tools.py
pocketutils/tools/path_tools.py
pocketutils/tools/program_tools.py
pocketutils/tools/reflection_tools.py
pocketutils/tools/string_tools.py
pocketutils/tools/sys_tools.py
pocketutils/tools/unit_tools.py
pocketutils-0.9.1.dist-info/LICENSE.txt
pocketutils-0.9.1.dist-info/WHEEL
pocketutils-0.9.1.dist-info/METADATA
pocketutils-0.9.1.dist-info/RECORD
