Metadata-Version: 2.1
Name: pocketutils
Version: 0.9.1
Summary: Adorable little Python code for you to copy or import.
Home-page: https://github.com/dmyersturnbull/pocketutils
License: Apache-2.0
Keywords: python,snippets,utils,gists,bioinformatics
Author: Douglas Myers-Turnbull
Maintainer: Douglas Myers-Turnbull
Requires-Python: >=3.8,<4.0
Classifier: Development Status :: 3 - Alpha
Classifier: Intended Audience :: Developers
Classifier: License :: OSI Approved :: Apache Software License
Classifier: Natural Language :: English
Classifier: Operating System :: OS Independent
Classifier: Programming Language :: Python :: 3
Classifier: Programming Language :: Python :: 3 :: Only
Classifier: Programming Language :: Python :: 3.10
Classifier: Programming Language :: Python :: 3.11
Classifier: Programming Language :: Python :: 3.8
Classifier: Programming Language :: Python :: 3.9
Classifier: Topic :: Software Development :: Libraries :: Python Modules
Provides-Extra: all
Provides-Extra: biochem
Provides-Extra: misc
Provides-Extra: notebooks
Provides-Extra: plotting
Provides-Extra: tools
Requires-Dist: defusedxml (>=0.6,<1.0)
Requires-Dist: goatools (>=1,<2); extra == "biochem" or extra == "all"
Requires-Dist: ipython (>=7); extra == "notebooks" or extra == "all"
Requires-Dist: joblib (>=1,<2); extra == "tools" or extra == "all"
Requires-Dist: loguru (>=0.5,<1.0); extra == "tools" or extra == "all"
Requires-Dist: matplotlib (>=3,<4); extra == "plotting" or extra == "all"
Requires-Dist: notifiers (>=1,<2)
Requires-Dist: numpy (>=1.17,<2.0); extra == "tools" or extra == "plotting" or extra == "biochem" or extra == "all"
Requires-Dist: orjson (>=3,<4)
Requires-Dist: pandas (>=1,<2); extra == "tools" or extra == "plotting" or extra == "notebooks" or extra == "biochem" or extra == "all"
Requires-Dist: pint (>=0.10,<1.0); extra == "tools" or extra == "biochem" or extra == "all"
Requires-Dist: psutil (>=5); extra == "misc" or extra == "all"
Requires-Dist: regex (>=2019)
Requires-Dist: requests (>=2,<3); extra == "biochem" or extra == "all"
Requires-Dist: toml (>=0.10,<1.0)
Requires-Dist: tomlkit (>=0.5,<1.0)
Requires-Dist: typer (>=0.4,<1.0); extra == "misc" or extra == "all"
Requires-Dist: uniprot (>=1.3,<2.0); extra == "biochem" or extra == "all"
Project-URL: CI, https://github.com/dmyersturnbull/pocketutils/actions
Project-URL: Changelog, https://github.com/dmyersturnbull/pocketutils/blob/main/CHANGELOG.md
Project-URL: Documentation, https://pocketutils.readthedocs.io
Project-URL: Download, https://pypi.org/project/pocketutils/
Project-URL: Issues, https://github.com/dmyersturnbull/pocketutils/issues
Project-URL: Repository, https://github.com/dmyersturnbull/pocketutils
